{
	"info": {
		"_postman_id": "dee6fa3e-48de-407a-b29b-c8251a18c187",
		"name": "Upstack nodejs",
		"schema": "https://schema.getpostman.com/json/collection/v2.1.0/collection.json"
	},
	"item": [
		{
			"name": "User create",
			"request": {
				"method": "POST",
				"header": [
					{
						"key": "Content-Type",
						"name": "Content-Type",
						"value": "application/json",
						"type": "text"
					}
				],
				"body": {
					"mode": "raw",
					"raw": "{\n\t\"username\": \"johndoe\",\n\t\"firstName\": \"John\",\n\t\"lastName\": \"Doe\",\n\t\"email\": \"john@doe\",\n\t\"password\": \"1234\",\n\t\"role\": \"admin\"\n}"
				},
				"url": {
					"raw": "{{baseUrl}}/user",
					"host": [
						"{{baseUrl}}"
					],
					"path": [
						"user"
					]
				}
			},
			"response": []
		},
		{
			"name": "User update",
			"request": {
				"auth": {
					"type": "bearer",
					"bearer": [
						{
							"key": "token",
							"value": "{{token}}",
							"type": "string"
						}
					]
				},
				"method": "PUT",
				"header": [
					{
						"key": "Content-Type",
						"name": "Content-Type",
						"type": "text",
						"value": "application/json"
					}
				],
				"body": {
					"mode": "raw",
					"raw": "{\n\t\"username\": \"johndoe2\",\n\t\"firstName\": \"John2\",\n\t\"lastName\": \"Doe2\",\n\t\"email\": \"john@doe2\",\n\t\"password\": \"1234\",\n\t\"role\": \"admin\"\n}"
				},
				"url": {
					"raw": "{{baseUrl}}/user/1",
					"host": [
						"{{baseUrl}}"
					],
					"path": [
						"user",
						"1"
					]
				}
			},
			"response": []
		},
		{
			"name": "User delete",
			"request": {
				"auth": {
					"type": "bearer",
					"bearer": [
						{
							"key": "token",
							"value": "{{token}}",
							"type": "string"
						}
					]
				},
				"method": "DELETE",
				"header": [
					{
						"key": "Content-Type",
						"name": "Content-Type",
						"type": "text",
						"value": "application/json"
					}
				],
				"body": {
					"mode": "raw",
					"raw": ""
				},
				"url": {
					"raw": "{{baseUrl}}/user/1",
					"host": [
						"{{baseUrl}}"
					],
					"path": [
						"user",
						"1"
					]
				}
			},
			"response": []
		},
		{
			"name": "User verify",
			"request": {
				"method": "GET",
				"header": [
					{
						"key": "Content-Type",
						"name": "Content-Type",
						"type": "text",
						"value": "application/json"
					}
				],
				"body": {
					"mode": "raw",
					"raw": ""
				},
				"url": {
					"raw": "{{baseUrl}}/user/1/verify/provided-token",
					"host": [
						"{{baseUrl}}"
					],
					"path": [
						"user",
						"1",
						"verify",
						"provided-token"
					]
				}
			},
			"response": []
		},
		{
			"name": "User login",
			"event": [
				{
					"listen": "test",
					"script": {
						"id": "f0f5cce6-bcda-44ca-83c5-ea0e49faa68d",
						"exec": [
							"if (pm.response.to.have.status(201)) {",
							"    pm.environment.set(\"token\", pm.response.json().token);",
							"}"
						],
						"type": "text/javascript"
					}
				}
			],
			"request": {
				"method": "POST",
				"header": [
					{
						"key": "Content-Type",
						"name": "Content-Type",
						"type": "text",
						"value": "application/json"
					}
				],
				"body": {
					"mode": "raw",
					"raw": "{\n\t\"username\": \"johndoe\",\n\t\"password\": \"1234\"\n}"
				},
				"url": {
					"raw": "{{baseUrl}}/user/login",
					"host": [
						"{{baseUrl}}"
					],
					"path": [
						"user",
						"login"
					]
				}
			},
			"response": []
		},
		{
			"name": "User get by id",
			"request": {
				"auth": {
					"type": "bearer",
					"bearer": [
						{
							"key": "token",
							"value": "{{token}}",
							"type": "string"
						}
					]
				},
				"method": "GET",
				"header": [
					{
						"key": "Content-Type",
						"name": "Content-Type",
						"type": "text",
						"value": "application/json"
					}
				],
				"body": {
					"mode": "raw",
					"raw": ""
				},
				"url": {
					"raw": "{{baseUrl}}/user/71",
					"host": [
						"{{baseUrl}}"
					],
					"path": [
						"user",
						"71"
					]
				}
			},
			"response": []
		},
		{
			"name": "User get list",
			"request": {
				"auth": {
					"type": "bearer",
					"bearer": [
						{
							"key": "token",
							"value": "{{token}}",
							"type": "string"
						}
					]
				},
				"method": "GET",
				"header": [
					{
						"key": "Content-Type",
						"name": "Content-Type",
						"type": "text",
						"value": "application/json"
					}
				],
				"body": {
					"mode": "raw",
					"raw": ""
				},
				"url": {
					"raw": "{{baseUrl}}/user",
					"host": [
						"{{baseUrl}}"
					],
					"path": [
						"user"
					]
				}
			},
			"response": []
		}
	]
}